{"reqHeader":{"Host":"10.10.10.10:9013","Connection":"keep-alive","Upgrade-Insecure-Requests":"1","User-Agent":"Mozilla/5.0 (Windows NT 6.1; Win64; x64) AppleWebKit/537.36 (KHTML, like Gecko) Chrome/56.0.2924.87 Safari/537.36","Accept":"text/html,application/xhtml xml,application/xml;q=0.9,image/webp,*/*;q=0.8","Referer":"http://10.10.10.10:9014/","Accept-Encoding":"gzip, deflate, sdch","Accept-Language":"zh-CN,zh;q=0.8","Cookie":"JSESSIONID=11111; TGC=111"},"method":"GET","reqParams":{"service":"http://10.10.10.10:9014"},"reasonPhrase":"Found","rspHeader":{"Server":"Apache-Coyote/1.1","Cache-Control":"no-store","Set-Cookie":"123=\"\"; Expires=Thu, 01-Jan-1970 00:00:10 GMT; Path=/; Secure","Pragma":"no-cache","Expires":"Thu, 01 Jan 1970 00:00:00 GMT","Location":"http://10.10.10.10:9014","Content-Length":"0","Date":"Tue, 14 Mar 2017 08:58:53 GMT"},"rspBody":{"flag":"1","msg":{"deptName":"测试1级部门","namePath":"测试1级部门","id":"456","usersSize":4,"priority":0,"idPath":"234/345/","children":[{"deptName":"测试2级部门a","namePath":"测试1级部门-测试2级部门a","id":"234","usersSize":0,"priority":0,"idPath":"567/345/234/","children":[],"pid":"890","pinyin":"CeShi2JiBuMen1","corpId":"456"},{"deptName":"测试2级部门c","namePath":"测试1级部门-测试2级部门c","id":"345","usersSize":0,"priority":0,"idPath":"123/345/567/","children":[],"pid":"789","pinyin":"CeShi2JiBuMenc","corpId":"345"},{"deptName":"测试2级部门b","namePath":"企业-测试1级部门-测试2级部门b","id":"2334","usersSize":2,"priority":0,"idPath":"789/567/234/","children":[],"pid":"123","pinyin":"1qa","corpId":"1234"}],"pid":"1234","pinyin":"CeShiBuMen","corpId":"1234"}},"url":"10.10.10.10:9013/logout","statusCode":300}